elasticsearch_dsl_async.py
elasticsearch_dsl_async-0.dist-info/WHEEL
elasticsearch_dsl_async-0.dist-info/METADATA
elasticsearch_dsl_async-0.dist-info/RECORD
